MANIFEST.in
README.rst
setup.py
wsgim_rip.py
wsgim_rip.egg-info/PKG-INFO
wsgim_rip.egg-info/SOURCES.txt
wsgim_rip.egg-info/dependency_links.txt
wsgim_rip.egg-info/requires.txt
wsgim_rip.egg-info/top_level.txt