Metadata-Version: 1.1
Name: wsgim-rip
Version: 0.1.0
Summary: WSGI middleware for setting real ip.
Home-page: https://github.com/bninja/wsgim-proxy
Author: egon
Author-email: egon@gb.com
License: BSD
Platform: any
Classifier: Environment :: Web Environment
Classifier: Intended Audience :: Developers
Classifier: License :: OSI Approved :: BSD License
Classifier: Operating System :: OS Independent
Classifier: Programming Language :: Python
Classifier: Topic :: Internet :: WWW/HTTP :: Dynamic Content
Classifier: Topic :: Software Development :: Libraries :: Python Modules
